{"cameraMode":{"drawMode":0,"name":"Shaded","section":"Shading Mode"},"sceneLighting":true,"audioPlay":false,"sceneViewState":{"m_AlwaysRefresh":false,"showFog":true,"showSkybox":true,"showFlares":true,"showImageEffects":true,"showParticleSystems":true,"showVisualEffectGraphs":true,"m_FxEnabled":true},"in2DMode":false,"pivot":{"x":543.8353881835938,"y":12.622322082519532,"z":389.3692932128906},"rotation":{"x":0.0704050064086914,"y":0.09858866780996323,"z":-0.006985953543335199,"w":0.99261873960495},"size":21.88387680053711,"orthographic":false}