{"cameraMode":{"drawMode":0,"name":"Shaded","section":"Shading Mode"},"sceneLighting":true,"audioPlay":false,"sceneViewState":{"m_AlwaysRefresh":false,"showFog":true,"showSkybox":true,"showFlares":true,"showImageEffects":true,"showParticleSystems":true,"showVisualEffectGraphs":true,"m_FxEnabled":true},"in2DMode":false,"pivot":{"x":536.8699340820313,"y":5.819822311401367,"z":375.11346435546877},"rotation":{"x":-0.027267057448625566,"y":0.9048994183540344,"z":-0.05840620398521423,"w":-0.4208437502384186},"size":12.12435531616211,"orthographic":false}